<annotation>
	<folder>collected_data</folder>
	<filename>0962.jpg</filename>
	<path>/home/prombo/car/CarND-Capstone/traffic_light/collected_data/0962.jpg</path>
	<source>
		<database>Unknown</database>
	</source>
	<size>
		<width>800</width>
		<height>600</height>
		<depth>3</depth>
	</size>
	<segmented>0</segmented>
	<object>
		<name>Red</name>
		<pose>Unspecified</pose>
		<truncated>0</truncated>
		<difficult>0</difficult>
		<bndbox>
			<xmin>129</xmin>
			<ymin>259</ymin>
			<xmax>179</xmax>
			<ymax>380</ymax>
		</bndbox>
	</object>
	<object>
		<name>Red</name>
		<pose>Unspecified</pose>
		<truncated>0</truncated>
		<difficult>0</difficult>
		<bndbox>
			<xmin>376</xmin>
			<ymin>263</ymin>
			<xmax>428</xmax>
			<ymax>388</ymax>
		</bndbox>
	</object>
	<object>
		<name>Red</name>
		<pose>Unspecified</pose>
		<truncated>0</truncated>
		<difficult>0</difficult>
		<bndbox>
			<xmin>623</xmin>
			<ymin>268</ymin>
			<xmax>677</xmax>
			<ymax>389</ymax>
		</bndbox>
	</object>
</annotation>
